{
  "cable_holder_1": {
    "area": 2369.9263,
    "bbox": [
      21.508,
      20.7,
      23.34648
    ],
    "com": [
      0.0,
      -11.4806,
      4.60926
    ],
    "edges": 129,
    "faces": 52,
    "solids": 1,
    "vertices": 80,
    "volume": 2897.4924
  },
  "cable_holder_2": {
    "area": 4763.8195,
    "bbox": [
      46.016,
      20.7,
      23.34648
    ],
    "com": [
      0.0,
      -11.43563,
      4.46952
    ],
    "edges": 214,
    "faces": 82,
    "solids": 1,
    "vertices": 136,
    "volume": 5976.5216
  },
  "cable_holder_3": {
    "area": 7157.7127,
    "bbox": [
      70.524,
      20.7,
      23.34648
    ],
    "com": [
      0.0,
      -11.42124,
      4.4248
    ],
    "edges": 299,
    "faces": 112,
    "solids": 1,
    "vertices": 192,
    "volume": 9055.5508
  },
  "cable_holder_4": {
    "area": 9551.606,
    "bbox": [
      95.032,
      20.7,
      23.34648
    ],
    "com": [
      0.0,
      -11.41415,
      4.40278
    ],
    "edges": 384,
    "faces": 142,
    "solids": 1,
    "vertices": 248,
    "volume": 12134.58
  },
  "cable_holder_5": {
    "area": 11945.4992,
    "bbox": [
      119.54,
      20.7,
      23.34648
    ],
    "com": [
      0.0,
      -11.40993,
      4.38967
    ],
    "edges": 469,
    "faces": 172,
    "solids": 1,
    "vertices": 304,
    "volume": 15213.6092
  },
  "cable_holder_6": {
    "area": 14339.3925,
    "bbox": [
      144.048,
      20.7,
      23.34648
    ],
    "com": [
      0.0,
      -11.40714,
      4.38098
    ],
    "edges": 554,
    "faces": 202,
    "solids": 1,
    "vertices": 360,
    "volume": 18292.6384
  },
  "split_ball_3.0_mm": {
    "area": 824.4413,
    "bbox": [
      15.98999,
      15.71623,
      11.0
    ],
    "com": [
      0.46784,
      0.00018,
      -2.98413
    ],
    "edges": 302,
    "faces": 120,
    "solids": 1,
    "vertices": 202,
    "volume": 1002.0293
  },
  "split_ball_3.1_mm": {
    "area": 818.8924,
    "bbox": [
      15.98999,
      15.69681,
      11.0
    ],
    "com": [
      0.46777,
      -0.0,
      -2.99271
    ],
    "edges": 230,
    "faces": 92,
    "solids": 1,
    "vertices": 154,
    "volume": 999.0218
  },
  "split_ball_3.2_mm": {
    "area": 821.2513,
    "bbox": [
      15.98999,
      15.67673,
      11.0
    ],
    "com": [
      0.46802,
      2e-05,
      -3.00289
    ],
    "edges": 284,
    "faces": 113,
    "solids": 1,
    "vertices": 190,
    "volume": 995.0457
  },
  "split_ball_3.3_mm": {
    "area": 820.2606,
    "bbox": [
      15.98999,
      15.65599,
      11.0
    ],
    "com": [
      0.46807,
      0.00017,
      -3.01266
    ],
    "edges": 284,
    "faces": 113,
    "solids": 1,
    "vertices": 190,
    "volume": 991.3026
  },
  "split_ball_3.4_mm": {
    "area": 818.3638,
    "bbox": [
      15.98999,
      15.63458,
      11.0
    ],
    "com": [
      0.46792,
      -1e-05,
      -3.02244
    ],
    "edges": 266,
    "faces": 106,
    "solids": 1,
    "vertices": 178,
    "volume": 987.5283
  },
  "split_ball_3.5_mm": {
    "area": 818.2407,
    "bbox": [
      15.98999,
      15.61249,
      11.0
    ],
    "com": [
      0.46803,
      2e-05,
      -3.03279
    ],
    "edges": 284,
    "faces": 113,
    "solids": 1,
    "vertices": 190,
    "volume": 983.4491
  },
  "split_ball_3.6_mm": {
    "area": 818.272,
    "bbox": [
      15.98999,
      15.58974,
      11.0
    ],
    "com": [
      0.46806,
      0.0001,
      -3.04325
    ],
    "edges": 302,
    "faces": 120,
    "solids": 1,
    "vertices": 202,
    "volume": 979.2307
  },
  "split_ball_3.7_mm": {
    "area": 814.1025,
    "bbox": [
      15.98999,
      15.56631,
      11.0
    ],
    "com": [
      0.46756,
      -7e-05,
      -3.05336
    ],
    "edges": 248,
    "faces": 99,
    "solids": 1,
    "vertices": 166,
    "volume": 975.3253
  },
  "split_ball_3.8_mm": {
    "area": 817.1905,
    "bbox": [
      15.98999,
      15.5422,
      11.0
    ],
    "com": [
      0.46771,
      0.00032,
      -3.06456
    ],
    "edges": 320,
    "faces": 127,
    "solids": 1,
    "vertices": 214,
    "volume": 970.5477
  },
  "split_ball_3.9_mm": {
    "area": 815.0163,
    "bbox": [
      15.98999,
      15.51741,
      11.0
    ],
    "com": [
      0.46734,
      0.00024,
      -3.07529
    ],
    "edges": 302,
    "faces": 120,
    "solids": 1,
    "vertices": 202,
    "volume": 966.1942
  },
  "split_ball_4.0_mm": {
    "area": 813.1553,
    "bbox": [
      15.98999,
      15.49193,
      11.0
    ],
    "com": [
      0.46699,
      0.00036,
      -3.08618
    ],
    "edges": 284,
    "faces": 113,
    "solids": 1,
    "vertices": 190,
    "volume": 961.6822
  },
  "split_ball_4.1_mm": {
    "area": 807.8766,
    "bbox": [
      15.98999,
      15.46577,
      11.0
    ],
    "com": [
      0.46645,
      0.0001,
      -3.09688
    ],
    "edges": 212,
    "faces": 85,
    "solids": 1,
    "vertices": 142,
    "volume": 957.4079
  },
  "split_ball_4.2_mm": {
    "area": 809.7037,
    "bbox": [
      15.98999,
      15.43891,
      11.0
    ],
    "com": [
      0.46619,
      0.00019,
      -3.10859
    ],
    "edges": 266,
    "faces": 106,
    "solids": 1,
    "vertices": 178,
    "volume": 952.2848
  }
}
